[
  {
    "subject": "Just a simple task",
    "body": "visma",
    "url": "https://minside.login.top.no",
    "tags": [],
    "createdAt": "2015-12-07T12:50:22.745Z",
    "createdByUid": "riemann",
    "createdByName": "riemann",
    "modifiedAt": "2015-12-07T12:50:22.745Z"
  },
  {
    "subject": "Another simple task",
    "body": "compilio",
    "url": "https://tfk.klos7.no",
    "uid": "riemann",
    "tags": [],
    "createdAt": "2015-12-07T12:50:51.752Z",
    "modifiedAt": "2015-12-07T12:50:51.752Z"
  },
  {
    "subject": "We are all simple tasks",
    "body": "compilio",
    "url": "https://tfk.klos7.no",
    "uid": "riemann",
    "tags": [],
    "createdAt": "2015-12-09T13:00:51.752Z",
    "modifiedAt": "2015-12-09T13:00:51.752Z"
  },
  {
    "subject": "Just a simple task",
    "body": "visma",
    "url": "https://minside.login.top.no",
    "uid": "gauss",
    "tags": [],
    "createdAt": "2015-12-07T12:50:22.745Z",
    "modifiedAt": "2015-12-07T12:50:22.745Z"
  },
  {
    "subject": "Another simple task",
    "body": "compilio",
    "url": "https://tfk.klos7.no",
    "uid": "gauss",
    "tags": [],
    "createdAt": "2015-12-07T12:50:51.752Z"
  },
  {
    "subject": "We are all simple tasks",
    "body": "compilio",
    "url": "https://tfk.klos7.no",
    "uid": "gauss",
    "tags": [],
    "createdAt": "2015-12-09T13:00:51.752Z"
  }
]